LICENSE
MANIFEST.in
README.md
setup.py
climetlab_plugin_tools/__init__.py
climetlab_plugin_tools/create_plugin_cmd.py
climetlab_plugin_tools/str_utils.py
climetlab_plugin_tools/version
climetlab_plugin_tools.egg-info/PKG-INFO
climetlab_plugin_tools.egg-info/SOURCES.txt
climetlab_plugin_tools.egg-info/dependency_links.txt
climetlab_plugin_tools.egg-info/entry_points.txt
climetlab_plugin_tools.egg-info/requires.txt
climetlab_plugin_tools.egg-info/top_level.txt
climetlab_plugin_tools.egg-info/zip-safe
climetlab_plugin_tools/templates/dataset/.gitignore
climetlab_plugin_tools/templates/dataset/AUTHORS.rst
climetlab_plugin_tools/templates/dataset/CONTRIBUTORS.md
climetlab_plugin_tools/templates/dataset/LICENSE
climetlab_plugin_tools/templates/dataset/MANIFEST.in
climetlab_plugin_tools/templates/dataset/README.md
climetlab_plugin_tools/templates/dataset/makefile
climetlab_plugin_tools/templates/dataset/requirements.txt
climetlab_plugin_tools/templates/dataset/requirements_dev.txt
climetlab_plugin_tools/templates/dataset/setup.py
climetlab_plugin_tools/templates/dataset/tox.ini
climetlab_plugin_tools/templates/dataset/.github/ISSUE_TEMPLATE.md
climetlab_plugin_tools/templates/dataset/.github/workflows/check-and-publish.yml
climetlab_plugin_tools/templates/dataset/climetlab_plugin_name_climetlab_template/__init__.py
climetlab_plugin_tools/templates/dataset/climetlab_plugin_name_climetlab_template/dataset_name_climetlab_template.py
climetlab_plugin_tools/templates/dataset/climetlab_plugin_name_climetlab_template/version
climetlab_plugin_tools/templates/dataset/notebooks/demo_dataset_name_climetlab_template.ipynb
climetlab_plugin_tools/templates/dataset/tests/requirements_tests.txt
climetlab_plugin_tools/templates/dataset/tests/test_dataset_name_climetlab_template.py
climetlab_plugin_tools/templates/dataset/tests/test_notebooks.py
climetlab_plugin_tools/templates/source/.gitignore
climetlab_plugin_tools/templates/source/AUTHORS.rst
climetlab_plugin_tools/templates/source/CONTRIBUTORS.md
climetlab_plugin_tools/templates/source/LICENSE
climetlab_plugin_tools/templates/source/MANIFEST.in
climetlab_plugin_tools/templates/source/README.md
climetlab_plugin_tools/templates/source/makefile
climetlab_plugin_tools/templates/source/requirements.txt
